biosimulators_amici/__init__.py
biosimulators_amici/__main__.py
biosimulators_amici/core.py
biosimulators_amici/data_model.py
biosimulators_amici-0.1.30.dist-info/licenses/LICENSE
docs/.nojekyll
docs/about.html
docs/genindex.html
docs/index.html
docs/installation.html
docs/py-modindex.html
docs/search.html
docs/searchindex.js
docs/tutorial.html
docs/_static/alabaster.css
docs/_static/base-stemmer.js
docs/_static/basic.css
docs/_static/biosimulators-logo.svg
docs/_static/custom.css
docs/_static/doctools.js
docs/_static/documentation_options.js
docs/_static/english-stemmer.js
docs/_static/file.png
docs/_static/jquery-3.5.1.js
docs/_static/jquery.js
docs/_static/language_data.js
docs/_static/minus.png
docs/_static/plus.png
docs/_static/pygments.css
docs/_static/searchtools.js
docs/_static/sphinx_highlight.js
docs/_static/underscore-1.12.0.js
docs/_static/underscore-1.13.1.js
docs/_static/underscore-1.3.1.js
docs/_static/underscore.js
docs/_static/webpack-macros.html
docs/_static/css/biosimulators.css
docs/_static/css/blank.css
docs/_static/css/index.c5995385ac14fb8791e8eb36b4908be2.css
docs/_static/css/index.ff1ffe594081f20da1ef19478df9384b.css
docs/_static/css/theme.css
docs/_static/js/index.1c5a1a01449ed65a7b51.js
docs/_static/js/index.be7d3bbb2ef33a8344ce.js
docs/_static/scripts/bootstrap.js
docs/_static/scripts/bootstrap.js.LICENSE.txt
docs/_static/scripts/bootstrap.js.map
docs/_static/scripts/fontawesome.js
docs/_static/scripts/fontawesome.js.LICENSE.txt
docs/_static/scripts/fontawesome.js.map
docs/_static/scripts/pydata-sphinx-theme.js
docs/_static/scripts/pydata-sphinx-theme.js.map
docs/_static/styles/bootstrap.css
docs/_static/styles/pydata-sphinx-theme.css
docs/_static/styles/pydata-sphinx-theme.css.map
docs/_static/styles/theme.css
docs/_static/vendor/fontawesome/5.13.0/LICENSE.txt
docs/_static/vendor/fontawesome/5.13.0/css/all.min.css
docs/_static/vendor/fontawesome/5.13.0/webfonts/fa-brands-400.eot
docs/_static/vendor/fontawesome/5.13.0/webfonts/fa-brands-400.svg
biosimulators_amici-0.1.30.dist-info/METADATA
biosimulators_amici-0.1.30.dist-info/WHEEL
biosimulators_amici-0.1.30.dist-info/entry_points.txt
biosimulators_amici-0.1.30.dist-info/top_level.txt
biosimulators_amici-0.1.30.dist-info/RECORD
