Metadata-Version: 2.4
Name: biosimulators_amici
Version: 0.1.30
Summary: BioSimulators-compliant command-line interface to the AMICI simulation program <https://github.com/AMICI-dev/amici>.
Author-email: Center for Reproducible Biomedical Modeling <info@biosimulators.org>
License-Expression: MIT
Project-URL: Homepage, https://github.com/biosimulators/Biosimulators_AMICI
Project-URL: Download, https://github.com/biosimulators/Biosimulators_AMICI
Keywords: BioSimulators,systems biology,computational biology,mathematical model,kinetic model,simulation,SBML,SED-ML,COMBINE,OMEX
Classifier: Development Status :: 3 - Alpha
Classifier: Intended Audience :: Science/Research
Classifier: Topic :: Scientific/Engineering :: Bio-Informatics
Requires-Python: >=3.11
License-File: LICENSE
Requires-Dist: biosimulators-utils[logging]>=0.1.180
Requires-Dist: amici<1.0.0,>=0.34.0
Requires-Dist: kisao>=2.33
Requires-Dist: lxml
Requires-Dist: numpy
Provides-Extra: tests
Requires-Dist: biosimulators_utils[containers]; extra == "tests"
Requires-Dist: python_dateutil; extra == "tests"
Provides-Extra: doc
Requires-Dist: pydata-sphinx-theme; extra == "doc"
Requires-Dist: sphinx>=1.8; extra == "doc"
Provides-Extra: all
Requires-Dist: biosimulators_utils[containers]; extra == "all"
Requires-Dist: python_dateutil; extra == "all"
Requires-Dist: pydata-sphinx-theme; extra == "all"
Requires-Dist: sphinx>=1.8; extra == "all"
Dynamic: license-file
